{
  "prNumber": 66,
  "owner": "Ascend",
  "repo": "MindIE-PyMotor",
  "createdAt": "2026-04-03T15:05:26+08:00",
  "mergedAt": "2026-04-03T17:36:36+08:00",
  "prSubmitToMerge": {
    "durationSeconds": 9070,
    "fromTime": "2026-04-03T15:05:26Z",
    "toTime": "2026-04-03T17:36:36Z"
  },
  "compileToCiCycles": [
    {
      "compileTime": "2026-04-03T15:11:02Z",
      "startTime": "2026-04-03T15:11:28Z",
      "finishTime": "2026-04-03T15:20:49Z",
      "durationSeconds": 587
    },
    {
      "compileTime": "2026-04-03T16:19:44Z",
      "startTime": "2026-04-03T16:20:14Z",
      "finishTime": "2026-04-03T16:30:07Z",
      "durationSeconds": 623
    },
    {
      "compileTime": "2026-04-03T16:39:06Z",
      "startTime": "2026-04-03T16:39:31Z",
      "finishTime": "2026-04-03T16:51:11Z",
      "durationSeconds": 725
    },
    {
      "compileTime": "2026-04-03T16:54:45Z",
      "startTime": "2026-04-03T16:56:13Z",
      "finishTime": "2026-04-03T17:06:41Z",
      "durationSeconds": 716
    },
    {
      "compileTime": "2026-04-03T15:11:02Z",
      "startTime": "2026-04-03T15:22:16Z",
      "finishTime": "2026-04-03T15:24:05Z",
      "durationSeconds": 783
    },
    {
      "compileTime": "2026-04-03T16:19:44Z",
      "startTime": "2026-04-03T16:20:49Z",
      "finishTime": "2026-04-03T16:23:01Z",
      "durationSeconds": 197
    },
    {
      "compileTime": "2026-04-03T16:39:06Z",
      "startTime": "2026-04-03T16:45:12Z",
      "finishTime": "2026-04-03T16:47:16Z",
      "durationSeconds": 490
    },
    {
      "compileTime": "2026-04-03T16:54:45Z",
      "startTime": "2026-04-03T17:00:05Z",
      "finishTime": "2026-04-03T17:01:51Z",
      "durationSeconds": 426
    }
  ],
  "lastCiRemovalToMerge": {
    "durationSeconds": 0,
    "fromTime": "2026-04-04T01:06:41Z",
    "toTime": "2026-04-03T17:36:36Z"
  }
}