{
  "prNumber": 76,
  "owner": "Ascend",
  "repo": "MindIE-PyMotor",
  "createdAt": "2026-04-10T09:17:23+08:00",
  "mergedAt": "2026-04-10T11:43:35+08:00",
  "prSubmitToMerge": {
    "durationSeconds": 8772,
    "fromTime": "2026-04-10T09:17:23Z",
    "toTime": "2026-04-10T11:43:35Z"
  },
  "compileToCiCycles": [
    {
      "compileTime": "2026-04-10T09:17:58Z",
      "startTime": "2026-04-10T09:18:21Z",
      "finishTime": "2026-04-10T09:25:46Z",
      "durationSeconds": 468
    },
    {
      "compileTime": "2026-04-10T09:45:39Z",
      "startTime": "2026-04-10T09:46:06Z",
      "finishTime": "2026-04-10T09:51:56Z",
      "durationSeconds": 377
    },
    {
      "compileTime": "2026-04-10T11:11:14Z",
      "startTime": "2026-04-10T11:11:40Z",
      "finishTime": "2026-04-10T11:18:12Z",
      "durationSeconds": 418
    },
    {
      "compileTime": "2026-04-10T09:17:58Z",
      "startTime": "2026-04-10T09:18:44Z",
      "finishTime": "2026-04-10T09:20:54Z",
      "durationSeconds": 176
    },
    {
      "compileTime": "2026-04-10T09:45:39Z",
      "startTime": "2026-04-10T09:46:57Z",
      "finishTime": "2026-04-10T09:48:39Z",
      "durationSeconds": 180
    },
    {
      "compileTime": "2026-04-10T11:11:14Z",
      "startTime": "2026-04-10T11:14:03Z",
      "finishTime": "2026-04-10T11:16:27Z",
      "durationSeconds": 313
    }
  ],
  "lastCiRemovalToMerge": {
    "durationSeconds": 0,
    "fromTime": "2026-04-10T19:18:12Z",
    "toTime": "2026-04-10T11:43:35Z"
  }
}