{
  "prNumber": 14,
  "owner": "Ascend",
  "repo": "MindStudio-Tools-Extension-Library",
  "createdAt": "2026-03-28T10:27:03+08:00",
  "mergedAt": "2026-03-28T14:47:14+08:00",
  "prSubmitToMerge": {
    "durationSeconds": 15611,
    "fromTime": "2026-03-28T10:27:03Z",
    "toTime": "2026-03-28T14:47:14Z"
  },
  "compileToCiCycles": [
    {
      "compileTime": "2026-03-28T10:37:52Z",
      "startTime": "2026-03-28T10:38:30Z",
      "finishTime": "2026-03-28T10:53:03Z",
      "durationSeconds": 911
    },
    {
      "compileTime": "2026-03-28T10:52:51Z",
      "startTime": "2026-03-28T10:55:00Z",
      "finishTime": "2026-03-28T10:53:03Z",
      "durationSeconds": 12
    },
    {
      "compileTime": "2026-03-28T11:04:28Z",
      "startTime": "2026-03-28T11:08:48Z",
      "finishTime": "2026-03-28T11:15:53Z",
      "durationSeconds": 685
    },
    {
      "compileTime": "2026-03-28T10:37:52Z",
      "startTime": "2026-03-28T10:38:55Z",
      "finishTime": "2026-03-28T10:40:32Z",
      "durationSeconds": 160
    },
    {
      "compileTime": "2026-03-28T10:52:51Z",
      "startTime": "2026-03-28T10:53:55Z",
      "finishTime": "2026-03-28T10:54:54Z",
      "durationSeconds": 123
    },
    {
      "compileTime": "2026-03-28T11:04:28Z",
      "startTime": "2026-03-28T11:05:52Z",
      "finishTime": "2026-03-28T11:08:07Z",
      "durationSeconds": 219
    }
  ],
  "lastCiRemovalToMerge": {
    "durationSeconds": 0,
    "fromTime": "2026-03-28T19:15:53Z",
    "toTime": "2026-03-28T14:47:14Z"
  }
}