{
  "prNumber": 32,
  "owner": "Ascend",
  "repo": "MindStudio-Tools-Extension-Library",
  "createdAt": "2026-04-23T23:06:51+08:00",
  "mergedAt": null,
  "prSubmitToMerge": null,
  "compileToCiCycles": [
    {
      "compileTime": "2026-04-23T15:07:08Z",
      "startTime": "2026-04-23T15:07:44Z",
      "finishTime": "2026-04-23T15:12:49Z",
      "durationSeconds": 341
    },
    {
      "compileTime": "2026-04-23T15:07:08Z",
      "startTime": "2026-04-23T15:07:38Z",
      "finishTime": "2026-04-23T19:21:52Z",
      "durationSeconds": 15284
    }
  ],
  "lastCiRemovalToMerge": null
}