{
  "prNumber": 126,
  "owner": "Ascend",
  "repo": "MindStudio-Ops-Profiler",
  "createdAt": "2026-04-22T14:15:46+08:00",
  "mergedAt": "2026-04-22T15:10:09+08:00",
  "prSubmitToMerge": {
    "durationSeconds": 3263,
    "fromTime": "2026-04-22T06:15:46Z",
    "toTime": "2026-04-22T07:10:09Z"
  },
  "compileToCiCycles": [
    {
      "compileTime": "2026-04-22T06:18:14Z",
      "startTime": "2026-04-22T06:18:49Z",
      "finishTime": "2026-04-22T06:34:48Z",
      "durationSeconds": 994
    },
    {
      "compileTime": "2026-04-22T06:18:14Z",
      "startTime": "2026-04-22T06:18:44Z",
      "finishTime": "2026-04-22T07:10:09Z",
      "durationSeconds": 3115
    }
  ],
  "lastCiRemovalToMerge": {
    "durationSeconds": 0,
    "fromTime": "2026-04-22T07:10:09Z",
    "toTime": "2026-04-22T07:10:09Z"
  }
}