{
  "prNumber": 30,
  "owner": "Ascend",
  "repo": "MindStudio-Ops-Generator",
  "createdAt": "2026-03-31T16:55:07+08:00",
  "mergedAt": "2026-03-31T19:45:24+08:00",
  "prSubmitToMerge": {
    "durationSeconds": 10217,
    "fromTime": "2026-03-31T16:55:07Z",
    "toTime": "2026-03-31T19:45:24Z"
  },
  "compileToCiCycles": [
    {
      "compileTime": "2026-03-31T16:57:31Z",
      "startTime": "2026-03-31T17:02:03Z",
      "finishTime": "2026-03-31T17:09:57Z",
      "durationSeconds": 746
    },
    {
      "compileTime": "2026-03-31T17:00:53Z",
      "startTime": "2026-03-31T17:02:03Z",
      "finishTime": "2026-03-31T17:09:57Z",
      "durationSeconds": 544
    },
    {
      "compileTime": "2026-03-31T16:57:31Z",
      "startTime": "2026-03-31T17:04:45Z",
      "finishTime": "2026-03-31T17:07:13Z",
      "durationSeconds": 582
    },
    {
      "compileTime": "2026-03-31T17:00:53Z",
      "startTime": "2026-03-31T17:04:45Z",
      "finishTime": "2026-03-31T17:07:13Z",
      "durationSeconds": 380
    }
  ],
  "lastCiRemovalToMerge": {
    "durationSeconds": 0,
    "fromTime": "2026-04-01T01:09:57Z",
    "toTime": "2026-03-31T19:45:24Z"
  }
}