{
  "prNumber": 8,
  "owner": "Ascend",
  "repo": "MindStudio-CommReport",
  "createdAt": "2026-03-31T20:49:16+08:00",
  "mergedAt": "2026-04-02T09:48:54+08:00",
  "prSubmitToMerge": {
    "durationSeconds": 133178,
    "fromTime": "2026-03-31T20:49:16Z",
    "toTime": "2026-04-02T09:48:54Z"
  },
  "compileToCiCycles": [
    {
      "compileTime": "2026-03-31T20:52:49Z",
      "startTime": "2026-03-31T20:53:24Z",
      "finishTime": "2026-03-31T21:03:45Z",
      "durationSeconds": 656
    },
    {
      "compileTime": "2026-03-31T20:52:49Z",
      "startTime": "2026-03-31T20:53:19Z",
      "finishTime": "2026-04-02T09:48:54Z",
      "durationSeconds": 132965
    }
  ],
  "lastCiRemovalToMerge": {
    "durationSeconds": 0,
    "fromTime": "2026-04-02T17:48:54Z",
    "toTime": "2026-04-02T09:48:54Z"
  }
}