{
  "prNumber": 34174,
  "owner": "Ascend",
  "repo": "pytorch",
  "createdAt": "2026-04-22T17:01:24+08:00",
  "mergedAt": null,
  "prSubmitToMerge": null,
  "compileToCiCycles": [
    {
      "compileTime": "2026-04-22T09:01:44Z",
      "startTime": "2026-04-22T09:02:40Z",
      "finishTime": "2026-04-22T10:08:20Z",
      "durationSeconds": 3996
    },
    {
      "compileTime": "2026-04-22T09:01:44Z",
      "startTime": "2026-04-22T09:02:14Z",
      "finishTime": "2026-04-23T08:27:04Z",
      "durationSeconds": 84320
    }
  ],
  "lastCiRemovalToMerge": null
}