{
  "prNumber": 33784,
  "owner": "Ascend",
  "repo": "pytorch",
  "createdAt": "2026-04-15T17:29:24+08:00",
  "mergedAt": "2026-04-21T17:19:22+08:00",
  "prSubmitToMerge": {
    "durationSeconds": 517798,
    "fromTime": "2026-04-15T09:29:24Z",
    "toTime": "2026-04-21T09:19:22Z"
  },
  "compileToCiCycles": [
    {
      "compileTime": "2026-04-15T09:29:33Z",
      "startTime": "2026-04-15T09:30:13Z",
      "finishTime": "2026-04-15T10:29:43Z",
      "durationSeconds": 3610
    },
    {
      "compileTime": "2026-04-15T09:29:33Z",
      "startTime": "2026-04-15T09:30:03Z",
      "finishTime": "2026-04-21T09:19:22Z",
      "durationSeconds": 517789
    }
  ],
  "lastCiRemovalToMerge": {
    "durationSeconds": 0,
    "fromTime": "2026-04-21T09:19:22Z",
    "toTime": "2026-04-21T09:19:22Z"
  }
}