{
  "prNumber": 33254,
  "owner": "Ascend",
  "repo": "pytorch",
  "createdAt": "2026-04-07T20:10:45+08:00",
  "mergedAt": null,
  "prSubmitToMerge": null,
  "compileToCiCycles": [
    {
      "compileTime": "2026-04-07T12:45:48Z",
      "startTime": "2026-04-07T12:46:20Z",
      "finishTime": "2026-04-07T13:05:04Z",
      "durationSeconds": 1156
    },
    {
      "compileTime": "2026-04-08T08:29:32Z",
      "startTime": "2026-04-08T08:35:13Z",
      "finishTime": "2026-04-08T08:48:34Z",
      "durationSeconds": 1142
    },
    {
      "compileTime": "2026-04-08T08:48:59Z",
      "startTime": "2026-04-08T08:49:28Z",
      "finishTime": "2026-04-08T10:13:11Z",
      "durationSeconds": 5052
    },
    {
      "compileTime": "2026-04-09T02:48:33Z",
      "startTime": "2026-04-09T02:49:09Z",
      "finishTime": "2026-04-09T04:08:03Z",
      "durationSeconds": 4770
    },
    {
      "compileTime": "2026-04-09T08:04:38Z",
      "startTime": "2026-04-09T08:05:19Z",
      "finishTime": "2026-04-09T09:27:09Z",
      "durationSeconds": 4951
    },
    {
      "compileTime": "2026-04-20T14:13:45Z",
      "startTime": "2026-04-20T14:14:13Z",
      "finishTime": "2026-04-20T14:13:59Z",
      "durationSeconds": 14
    },
    {
      "compileTime": "2026-04-22T08:59:35Z",
      "startTime": "2026-04-22T09:00:10Z",
      "finishTime": "2026-04-22T09:19:32Z",
      "durationSeconds": 1197
    },
    {
      "compileTime": "2026-04-22T09:29:11Z",
      "startTime": "2026-04-22T09:46:08Z",
      "finishTime": "2026-04-22T09:50:43Z",
      "durationSeconds": 1292
    },
    {
      "compileTime": "2026-04-23T02:15:18Z",
      "startTime": "2026-04-23T02:36:34Z",
      "finishTime": "2026-04-23T03:19:21Z",
      "durationSeconds": 3843
    },
    {
      "compileTime": "2026-04-07T12:45:48Z",
      "startTime": "2026-04-07T12:46:18Z",
      "finishTime": "2026-04-23T03:19:21Z",
      "durationSeconds": 1348413
    },
    {
      "compileTime": "2026-04-08T08:29:32Z",
      "startTime": "2026-04-08T08:30:02Z",
      "finishTime": "2026-04-23T03:19:21Z",
      "durationSeconds": 1277389
    },
    {
      "compileTime": "2026-04-08T08:48:59Z",
      "startTime": "2026-04-08T08:49:29Z",
      "finishTime": "2026-04-23T03:19:21Z",
      "durationSeconds": 1276222
    },
    {
      "compileTime": "2026-04-09T02:48:33Z",
      "startTime": "2026-04-09T02:49:03Z",
      "finishTime": "2026-04-23T03:19:21Z",
      "durationSeconds": 1211448
    },
    {
      "compileTime": "2026-04-09T08:04:38Z",
      "startTime": "2026-04-09T08:05:08Z",
      "finishTime": "2026-04-23T03:19:21Z",
      "durationSeconds": 1192483
    },
    {
      "compileTime": "2026-04-20T14:13:45Z",
      "startTime": "2026-04-20T14:14:15Z",
      "finishTime": "2026-04-23T03:19:21Z",
      "durationSeconds": 219936
    },
    {
      "compileTime": "2026-04-22T08:59:35Z",
      "startTime": "2026-04-22T09:00:05Z",
      "finishTime": "2026-04-23T03:19:21Z",
      "durationSeconds": 65986
    },
    {
      "compileTime": "2026-04-22T09:29:11Z",
      "startTime": "2026-04-22T09:29:41Z",
      "finishTime": "2026-04-23T03:19:21Z",
      "durationSeconds": 64210
    },
    {
      "compileTime": "2026-04-23T02:15:18Z",
      "startTime": "2026-04-23T02:15:48Z",
      "finishTime": "2026-04-23T03:19:21Z",
      "durationSeconds": 3843
    }
  ],
  "lastCiRemovalToMerge": null
}