{
  "prNumber": 34204,
  "owner": "Ascend",
  "repo": "pytorch",
  "createdAt": "2026-04-23T10:30:07+08:00",
  "mergedAt": null,
  "prSubmitToMerge": null,
  "compileToCiCycles": [
    {
      "compileTime": "2026-04-23T02:31:20Z",
      "startTime": "2026-04-23T03:01:20Z",
      "finishTime": "2026-04-23T03:20:44Z",
      "durationSeconds": 2964
    },
    {
      "compileTime": "2026-04-23T02:31:20Z",
      "startTime": "2026-04-23T02:31:50Z",
      "finishTime": "2026-04-23T03:20:44Z",
      "durationSeconds": 2964
    }
  ],
  "lastCiRemovalToMerge": null
}