{
  "prNumber": 34017,
  "owner": "Ascend",
  "repo": "pytorch",
  "createdAt": "2026-04-20T16:08:34+08:00",
  "mergedAt": null,
  "prSubmitToMerge": null,
  "compileToCiCycles": [
    {
      "compileTime": "2026-04-20T08:08:40Z",
      "startTime": "2026-04-20T08:57:00Z",
      "finishTime": "2026-04-20T10:26:51Z",
      "durationSeconds": 8291
    },
    {
      "compileTime": "2026-04-20T14:01:48Z",
      "startTime": "2026-04-20T14:03:33Z",
      "finishTime": "2026-04-20T15:25:52Z",
      "durationSeconds": 5044
    },
    {
      "compileTime": "2026-04-20T08:08:40Z",
      "startTime": "2026-04-20T08:09:10Z",
      "finishTime": "2026-04-20T19:31:52Z",
      "durationSeconds": 40992
    },
    {
      "compileTime": "2026-04-20T14:01:48Z",
      "startTime": "2026-04-20T14:02:18Z",
      "finishTime": "2026-04-20T19:31:52Z",
      "durationSeconds": 19804
    }
  ],
  "lastCiRemovalToMerge": null
}