{
  "prNumber": 34153,
  "owner": "Ascend",
  "repo": "pytorch",
  "createdAt": "2026-04-22T11:49:32+08:00",
  "mergedAt": null,
  "prSubmitToMerge": null,
  "compileToCiCycles": [
    {
      "compileTime": "2026-04-22T03:50:53Z",
      "startTime": "2026-04-22T03:51:21Z",
      "finishTime": "2026-04-22T03:50:59Z",
      "durationSeconds": 6
    },
    {
      "compileTime": "2026-04-22T06:49:02Z",
      "startTime": "2026-04-22T06:54:21Z",
      "finishTime": "2026-04-22T06:49:14Z",
      "durationSeconds": 12
    },
    {
      "compileTime": "2026-04-22T06:53:52Z",
      "startTime": "2026-04-22T06:54:21Z",
      "finishTime": "2026-04-22T07:56:58Z",
      "durationSeconds": 3786
    },
    {
      "compileTime": "2026-04-22T03:50:53Z",
      "startTime": "2026-04-22T03:51:23Z",
      "finishTime": "2026-04-22T08:14:22Z",
      "durationSeconds": 15809
    },
    {
      "compileTime": "2026-04-22T06:49:02Z",
      "startTime": "2026-04-22T06:49:32Z",
      "finishTime": "2026-04-22T08:14:22Z",
      "durationSeconds": 5120
    },
    {
      "compileTime": "2026-04-22T06:53:52Z",
      "startTime": "2026-04-22T06:54:22Z",
      "finishTime": "2026-04-22T08:14:22Z",
      "durationSeconds": 4830
    }
  ],
  "lastCiRemovalToMerge": null
}