{
  "prNumber": 140,
  "owner": "Ascend",
  "repo": "MindStudio-Sanitizer",
  "createdAt": "2026-04-10T16:31:11+08:00",
  "mergedAt": "2026-04-14T09:51:57+08:00",
  "prSubmitToMerge": {
    "durationSeconds": 321646,
    "fromTime": "2026-04-10T16:31:11Z",
    "toTime": "2026-04-14T09:51:57Z"
  },
  "compileToCiCycles": [
    {
      "compileTime": "2026-04-10T16:36:04Z",
      "startTime": "2026-04-10T16:36:52Z",
      "finishTime": "2026-04-10T16:56:29Z",
      "durationSeconds": 1225
    },
    {
      "compileTime": "2026-04-10T17:29:15Z",
      "startTime": "2026-04-10T17:30:02Z",
      "finishTime": "2026-04-10T17:52:59Z",
      "durationSeconds": 1424
    },
    {
      "compileTime": "2026-04-10T16:36:04Z",
      "startTime": "2026-04-10T16:36:34Z",
      "finishTime": "2026-04-14T09:51:57Z",
      "durationSeconds": 321353
    },
    {
      "compileTime": "2026-04-10T17:29:15Z",
      "startTime": "2026-04-10T17:29:45Z",
      "finishTime": "2026-04-14T09:51:57Z",
      "durationSeconds": 318162
    }
  ],
  "lastCiRemovalToMerge": {
    "durationSeconds": 0,
    "fromTime": "2026-04-14T17:51:57Z",
    "toTime": "2026-04-14T09:51:57Z"
  }
}