{
  "prNumber": 149,
  "owner": "Ascend",
  "repo": "MindStudio-Sanitizer",
  "createdAt": "2026-04-16T11:29:28+08:00",
  "mergedAt": "2026-04-16T16:54:27+08:00",
  "prSubmitToMerge": {
    "durationSeconds": 19499,
    "fromTime": "2026-04-16T11:29:28Z",
    "toTime": "2026-04-16T16:54:27Z"
  },
  "compileToCiCycles": [
    {
      "compileTime": "2026-04-16T11:34:53Z",
      "startTime": "2026-04-16T11:35:27Z",
      "finishTime": "2026-04-16T11:39:12Z",
      "durationSeconds": 259
    },
    {
      "compileTime": "2026-04-16T14:31:34Z",
      "startTime": "2026-04-16T14:32:09Z",
      "finishTime": "2026-04-16T14:47:26Z",
      "durationSeconds": 952
    },
    {
      "compileTime": "2026-04-16T11:34:53Z",
      "startTime": "2026-04-16T11:35:23Z",
      "finishTime": "2026-04-16T16:54:27Z",
      "durationSeconds": 19174
    },
    {
      "compileTime": "2026-04-16T14:31:34Z",
      "startTime": "2026-04-16T14:32:04Z",
      "finishTime": "2026-04-16T16:54:27Z",
      "durationSeconds": 8573
    }
  ],
  "lastCiRemovalToMerge": {
    "durationSeconds": 0,
    "fromTime": "2026-04-17T00:54:27Z",
    "toTime": "2026-04-16T16:54:27Z"
  }
}