{
  "prNumber": 170,
  "owner": "Ascend",
  "repo": "MindStudio-Sanitizer",
  "createdAt": "2026-04-23T22:15:16+08:00",
  "mergedAt": null,
  "prSubmitToMerge": null,
  "compileToCiCycles": [
    {
      "compileTime": "2026-04-23T14:16:06Z",
      "startTime": "2026-04-23T14:16:48Z",
      "finishTime": "2026-04-23T14:43:25Z",
      "durationSeconds": 1639
    },
    {
      "compileTime": "2026-04-24T02:51:04Z",
      "startTime": "2026-04-24T02:51:39Z",
      "finishTime": "2026-04-24T03:02:24Z",
      "durationSeconds": 680
    },
    {
      "compileTime": "2026-04-23T14:16:06Z",
      "startTime": "2026-04-24T02:53:47Z",
      "finishTime": "2026-04-24T02:54:39Z",
      "durationSeconds": 45513
    },
    {
      "compileTime": "2026-04-24T02:51:04Z",
      "startTime": "2026-04-24T02:53:47Z",
      "finishTime": "2026-04-24T02:54:39Z",
      "durationSeconds": 215
    }
  ],
  "lastCiRemovalToMerge": null
}