{
  "prNumber": 93,
  "owner": "Ascend",
  "repo": "MindStudio-Sanitizer",
  "createdAt": "2026-03-16T19:17:29+08:00",
  "mergedAt": "2026-03-16T20:55:35+08:00",
  "prSubmitToMerge": {
    "durationSeconds": 5886,
    "fromTime": "2026-03-16T19:17:29Z",
    "toTime": "2026-03-16T20:55:35Z"
  },
  "compileToCiCycles": [
    {
      "compileTime": "2026-03-16T20:02:33Z",
      "startTime": "2026-03-16T20:03:22Z",
      "finishTime": "2026-03-16T20:20:54Z",
      "durationSeconds": 1101
    },
    {
      "compileTime": "2026-03-16T20:02:33Z",
      "startTime": "2026-03-16T20:02:58Z",
      "finishTime": "2026-03-16T20:03:28Z",
      "durationSeconds": 55
    }
  ],
  "lastCiRemovalToMerge": {
    "durationSeconds": 0,
    "fromTime": "2026-03-17T04:20:54Z",
    "toTime": "2026-03-16T20:55:35Z"
  }
}