{
  "prNumber": 97,
  "owner": "Ascend",
  "repo": "MindStudio-Sanitizer",
  "createdAt": "2026-03-19T10:08:04+08:00",
  "mergedAt": "2026-03-20T11:30:40+08:00",
  "prSubmitToMerge": {
    "durationSeconds": 91356,
    "fromTime": "2026-03-19T10:08:04Z",
    "toTime": "2026-03-20T11:30:40Z"
  },
  "compileToCiCycles": [
    {
      "compileTime": "2026-03-19T19:13:47Z",
      "startTime": "2026-03-19T19:14:30Z",
      "finishTime": "2026-03-19T19:18:44Z",
      "durationSeconds": 297
    },
    {
      "compileTime": "2026-03-19T19:36:23Z",
      "startTime": "2026-03-19T19:37:04Z",
      "finishTime": "2026-03-19T19:46:59Z",
      "durationSeconds": 636
    },
    {
      "compileTime": "2026-03-19T19:13:47Z",
      "startTime": "2026-03-19T19:14:13Z",
      "finishTime": "2026-03-19T19:14:43Z",
      "durationSeconds": 56
    },
    {
      "compileTime": "2026-03-19T19:36:23Z",
      "startTime": "2026-03-19T19:36:53Z",
      "finishTime": "2026-03-19T19:37:19Z",
      "durationSeconds": 56
    }
  ],
  "lastCiRemovalToMerge": {
    "durationSeconds": 27821,
    "fromTime": "2026-03-20T03:46:59Z",
    "toTime": "2026-03-20T11:30:40Z"
  }
}