{
  "prNumber": 2373,
  "owner": "Ascend",
  "repo": "MindSpeed-MM",
  "createdAt": "2026-04-08T16:51:09+08:00",
  "mergedAt": "2026-04-23T15:26:52+08:00",
  "prSubmitToMerge": {
    "durationSeconds": 1290943,
    "fromTime": "2026-04-08T08:51:09Z",
    "toTime": "2026-04-23T07:26:52Z"
  },
  "compileToCiCycles": [
    {
      "compileTime": "2026-04-08T08:55:25Z",
      "startTime": "2026-04-08T09:07:11Z",
      "finishTime": "2026-04-08T08:55:30Z",
      "durationSeconds": 5
    },
    {
      "compileTime": "2026-04-21T12:38:54Z",
      "startTime": "2026-04-21T13:41:45Z",
      "finishTime": "2026-04-21T12:39:10Z",
      "durationSeconds": 16
    },
    {
      "compileTime": "2026-04-21T13:26:51Z",
      "startTime": "2026-04-21T13:41:45Z",
      "finishTime": "2026-04-21T13:44:14Z",
      "durationSeconds": 1043
    },
    {
      "compileTime": "2026-04-22T01:15:43Z",
      "startTime": "2026-04-22T01:46:06Z",
      "finishTime": "2026-04-22T01:51:31Z",
      "durationSeconds": 2148
    },
    {
      "compileTime": "2026-04-22T01:16:32Z",
      "startTime": "2026-04-22T01:46:06Z",
      "finishTime": "2026-04-22T01:51:31Z",
      "durationSeconds": 2099
    },
    {
      "compileTime": "2026-04-22T06:45:55Z",
      "startTime": "2026-04-22T06:46:33Z",
      "finishTime": "2026-04-22T06:49:52Z",
      "durationSeconds": 237
    },
    {
      "compileTime": "2026-04-22T06:46:09Z",
      "startTime": "2026-04-22T06:46:33Z",
      "finishTime": "2026-04-22T06:49:52Z",
      "durationSeconds": 223
    },
    {
      "compileTime": "2026-04-22T11:51:02Z",
      "startTime": "2026-04-22T11:51:26Z",
      "finishTime": "2026-04-22T12:28:27Z",
      "durationSeconds": 2245
    },
    {
      "compileTime": "2026-04-08T08:55:25Z",
      "startTime": "2026-04-21T13:29:59Z",
      "finishTime": "2026-04-21T13:32:05Z",
      "durationSeconds": 1139800
    },
    {
      "compileTime": "2026-04-21T12:38:54Z",
      "startTime": "2026-04-21T13:29:59Z",
      "finishTime": "2026-04-21T13:32:05Z",
      "durationSeconds": 3191
    },
    {
      "compileTime": "2026-04-21T13:26:51Z",
      "startTime": "2026-04-21T13:29:59Z",
      "finishTime": "2026-04-21T13:32:05Z",
      "durationSeconds": 314
    },
    {
      "compileTime": "2026-04-22T01:15:43Z",
      "startTime": "2026-04-22T01:16:35Z",
      "finishTime": "2026-04-22T01:17:59Z",
      "durationSeconds": 136
    },
    {
      "compileTime": "2026-04-22T01:16:32Z",
      "startTime": "2026-04-22T01:16:35Z",
      "finishTime": "2026-04-22T01:17:59Z",
      "durationSeconds": 87
    },
    {
      "compileTime": "2026-04-22T06:45:55Z",
      "startTime": "2026-04-22T06:47:26Z",
      "finishTime": "2026-04-22T06:49:53Z",
      "durationSeconds": 238
    },
    {
      "compileTime": "2026-04-22T06:46:09Z",
      "startTime": "2026-04-22T06:47:26Z",
      "finishTime": "2026-04-22T06:49:53Z",
      "durationSeconds": 224
    },
    {
      "compileTime": "2026-04-22T11:51:02Z",
      "startTime": "2026-04-22T11:53:41Z",
      "finishTime": "2026-04-22T11:56:22Z",
      "durationSeconds": 320
    }
  ],
  "lastCiRemovalToMerge": {
    "durationSeconds": 68305,
    "fromTime": "2026-04-22T12:28:27Z",
    "toTime": "2026-04-23T07:26:52Z"
  }
}