{
  "prNumber": 4755,
  "owner": "Ascend",
  "repo": "op-plugin",
  "createdAt": "2026-04-20T19:41:54+08:00",
  "mergedAt": null,
  "prSubmitToMerge": null,
  "compileToCiCycles": [
    {
      "compileTime": "2026-04-20T11:42:23Z",
      "startTime": "2026-04-20T11:45:04Z",
      "finishTime": "2026-04-20T13:30:10Z",
      "durationSeconds": 6467
    },
    {
      "compileTime": "2026-04-20T14:24:43Z",
      "startTime": "2026-04-20T14:25:10Z",
      "finishTime": "2026-04-20T15:52:09Z",
      "durationSeconds": 5246
    },
    {
      "compileTime": "2026-04-21T03:02:26Z",
      "startTime": "2026-04-21T03:10:36Z",
      "finishTime": "2026-04-21T04:40:59Z",
      "durationSeconds": 5913
    },
    {
      "compileTime": "2026-04-21T11:40:40Z",
      "startTime": "2026-04-21T11:41:18Z",
      "finishTime": "2026-04-21T13:53:11Z",
      "durationSeconds": 7951
    },
    {
      "compileTime": "2026-04-20T11:42:23Z",
      "startTime": "2026-04-20T11:42:55Z",
      "finishTime": "2026-04-20T11:44:51Z",
      "durationSeconds": 148
    },
    {
      "compileTime": "2026-04-20T14:24:43Z",
      "startTime": "2026-04-20T14:26:20Z",
      "finishTime": "2026-04-20T14:28:08Z",
      "durationSeconds": 205
    },
    {
      "compileTime": "2026-04-21T03:02:26Z",
      "startTime": "2026-04-21T03:03:34Z",
      "finishTime": "2026-04-21T03:05:22Z",
      "durationSeconds": 176
    },
    {
      "compileTime": "2026-04-21T11:40:40Z",
      "startTime": "2026-04-21T11:43:50Z",
      "finishTime": "2026-04-21T11:45:55Z",
      "durationSeconds": 315
    }
  ],
  "lastCiRemovalToMerge": null
}